django_basemodels/__init__.py
django_basemodels/admin.py
django_basemodels/apps.py
django_basemodels/celery.py
django_basemodels/managers.py
django_basemodels/models.py
django_basemodels/query.py
django_basemodels/tasks.py
django_basemodels/test_app/__init__.py
django_basemodels/test_app/apps.py
django_basemodels/test_app/models.py
django_basemodels/test_app/settings.py
django_basemodels/utils.py
django_basemodels-0.0.5.dist-info/METADATA
django_basemodels-0.0.5.dist-info/WHEEL
django_basemodels-0.0.5.dist-info/RECORD
