Metadata-Version: 2.4
Name: django-basemodels
Version: 0.0.5
Summary: Базовая Django-модель с поддержкой полиморфизма и soft-delete (django-polymorphic, django-safedelete), автоматическим управлением активности и интеграцией с Celery.
Author: skulap
Author-email: skulap01@gmail.com
Requires-Python: >=3.12,<4.0
Classifier: Programming Language :: Python :: 3
Classifier: Programming Language :: Python :: 3.12
Classifier: Programming Language :: Python :: 3.13
Classifier: Programming Language :: Python :: 3.14
Provides-Extra: celery
Provides-Extra: standart
Requires-Dist: celery (>=5.5.3,<6.0.0) ; extra == "celery"
Requires-Dist: celery-hchecker (>=0.0.3,<0.0.4)
Requires-Dist: celery-hchecker (>=0.0.3,<0.0.4) ; extra == "celery"
Requires-Dist: django-celery-beat (>=2.8.1,<3.0.0) ; extra == "celery"
Requires-Dist: django-polymorphic (>=4.1.0,<5.0.0)
Requires-Dist: django-safedelete (>=1.4.1,<2.0.0)
